bitbucket/__init__.py
bitbucket/api.py
bitbucket_python_client-0.1.dist-info/LICENSE
bitbucket_python_client-0.1.dist-info/WHEEL
bitbucket_python_client-0.1.dist-info/METADATA
bitbucket_python_client-0.1.dist-info/RECORD
