Metadata-Version: 2.1
Name: bitbucket-python-client
Version: 0.1
Summary: A Python wrapper for the Bitbucket API.
Home-page: https://github.com/shmileee/bitbucket-python-client
License: UNKNOWN
Author: Oleksandr Ponomarov
Author-email: ponomarov.aleksandr@gmail.com
Classifier: License :: OSI Approved :: MIT License
Requires-Dist: requests==2.24.0
Requires-Dist: furl==2.1.0
Project-URL: Documentation, https://shmileee.github.io/bitbucket-python-client
